telegram_alert/__init__.py
telegram_alert/client.py
telegram_alert/config.py
telegram_alert/exceptions.py
telegram_alert/formatters.py
telegram_alert/py.typed
py_telegram_alert-0.2.0.dist-info/METADATA
py_telegram_alert-0.2.0.dist-info/WHEEL
py_telegram_alert-0.2.0.dist-info/licenses/LICENSE
py_telegram_alert-0.2.0.dist-info/RECORD
