Metadata-Version: 2.4
Name: py-telegram-alert
Version: 0.2.0
Summary: Simple, async-first Telegram alerts for Python
Project-URL: Homepage, https://github.com/cainky/telegram_alert
Project-URL: Repository, https://github.com/cainky/telegram_alert
Project-URL: Issues, https://github.com/cainky/telegram_alert/issues
Author-email: Kyle Cain <kylecain.me@gmail.com>
License-Expression: GPL-3.0-only
License-File: LICENSE
Keywords: alerts,async,bot,notifications,telegram
Classifier: Development Status :: 4 - Beta
Classifier: Framework :: AsyncIO
Classifier: Intended Audience :: Developers
Classifier: License :: OSI Approved :: GNU General Public License v3 (GPLv3)
Classifier: Programming Language :: Python :: 3
Classifier: Programming Language :: Python :: 3.11
Classifier: Programming Language :: Python :: 3.12
Classifier: Programming Language :: Python :: 3.13
Classifier: Topic :: Communications :: Chat
Classifier: Typing :: Typed
Requires-Python: >=3.11
Requires-Dist: httpx>=0.25
Requires-Dist: python-dotenv>=1.0
Provides-Extra: dev
Requires-Dist: pytest-asyncio>=0.23; extra == 'dev'
Requires-Dist: pytest>=8.0; extra == 'dev'
